{
  "graduate-wave": { "deck": "society", "tags": ["jobhunt", "youth"], "cooldown": 3, "bias": [{ "key": "tag:jobhunt", "mul": 1.1, "ttl": 6 }] },
  "civil-service-rush": { "deck": "exam", "tags": ["exam", "education"], "cooldown": 3, "enqueue": [{ "eventId": "queue:exam-result", "dueIn": 2, "priority": 75 }] },
  "social-security-pilot": { "deck": "policy", "tags": ["policy", "stability"], "cooldown": 5 },
  "ai-substitute": { "deck": "career", "tags": ["career", "layoff"], "cooldown": 5, "bias": [{ "key": "tag:layoff", "mul": 1.2, "ttl": 8 }] },
  "takeout-order-war": { "deck": "work", "tags": ["gig", "income"], "cooldown": 2 },
  "housing-rate-adjust": { "deck": "housing", "tags": ["mortgage", "debt"], "cooldown": 4, "enqueue": [{ "eventId": "queue:mortgage-followup", "dueIn": 2, "priority": 70 }] },
  "night-school-burst": { "deck": "exam", "tags": ["exam", "skill"], "cooldown": 2 },
  "rent-rise": { "deck": "housing", "tags": ["rent", "debt"], "cooldown": 3 },
  "medical-queue": { "deck": "health", "tags": ["health", "fatigue"], "cooldown": 3 },
  "livestream-burst": { "deck": "social", "tags": ["heat", "income"], "cooldown": 4 },
  "layoff-rumor": { "deck": "career", "tags": ["layoff", "jobhunt"], "cooldown": 4, "enqueue": [{ "eventId": "queue:jobhunt-feedback", "dueIn": 2, "priority": 72 }] },
  "blind-date": { "deck": "family", "tags": ["family", "relationship"], "cooldown": 4 },
  "mortgage-overdue": { "deck": "housing", "tags": ["mortgage", "debt"], "cooldown": 4 },
  "newborn": { "deck": "family", "tags": ["parenting", "family"], "cooldown": 6, "enqueue": [{ "eventId": "queue:parenting-support", "dueIn": 2, "priority": 78 }] },
  "second-child-discuss": { "deck": "family", "tags": ["parenting", "debt"], "cooldown": 6 },
  "child-sick-night": { "deck": "family", "tags": ["parenting", "health"], "cooldown": 4 },
  "helping-fall-fraud": { "deck": "social", "tags": ["legal", "heat"], "cooldown": 6, "setFlags": [{ "key": "legal.risk", "value": true, "ttl": 10 }] },
  "camera-clear": { "deck": "social", "tags": ["legal", "relief"], "cooldown": 6 },
  "divorce-asset-split": { "deck": "family", "tags": ["family", "debt"], "cooldown": 8 },
  "public-praise": { "deck": "social", "tags": ["heat", "morale"], "cooldown": 4 },
  "gold-price-spike": { "deck": "finance", "tags": ["finance", "heat"], "cooldown": 5 }
}
